Puppet27CookbookZhongwenban/README.md
Puppet27CookbookZhongwenban/__init__.py
Puppet27CookbookZhongwenban/__main__.py
Puppet27CookbookZhongwenban/file.epub
Puppet27CookbookZhongwenban/index.html
Puppet27CookbookZhongwenban/css/__init__.py
Puppet27CookbookZhongwenban/css/annotations.css
Puppet27CookbookZhongwenban/css/main.css
Puppet27CookbookZhongwenban/css/normalize.css
Puppet27CookbookZhongwenban/css/popup.css
Puppet27CookbookZhongwenban/font/__init__.py
Puppet27CookbookZhongwenban/font/fontello.eot
Puppet27CookbookZhongwenban/font/fontello.svg
Puppet27CookbookZhongwenban/font/fontello.ttf
Puppet27CookbookZhongwenban/font/fontello.woff
Puppet27CookbookZhongwenban/img/__init__.py
Puppet27CookbookZhongwenban/img/annotator-glyph-sprite.png
Puppet27CookbookZhongwenban/img/annotator-icon-sprite.png
Puppet27CookbookZhongwenban/img/apple-touch-icon.png
Puppet27CookbookZhongwenban/img/cancelfullscreen.png
Puppet27CookbookZhongwenban/img/close.png
Puppet27CookbookZhongwenban/img/fullscreen.png
Puppet27CookbookZhongwenban/img/loader.gif
Puppet27CookbookZhongwenban/img/menu-icon.png
Puppet27CookbookZhongwenban/img/save.png
Puppet27CookbookZhongwenban/img/saved.png
Puppet27CookbookZhongwenban/img/settings-s.png
Puppet27CookbookZhongwenban/img/settings.png
Puppet27CookbookZhongwenban/img/star.png
Puppet27CookbookZhongwenban/js/__init__.py
Puppet27CookbookZhongwenban/js/epub.js
Puppet27CookbookZhongwenban/js/epub.min.js
Puppet27CookbookZhongwenban/js/epub.min.map
Puppet27CookbookZhongwenban/js/hooks.min.js
Puppet27CookbookZhongwenban/js/hooks.min.map
Puppet27CookbookZhongwenban/js/reader.js
Puppet27CookbookZhongwenban/js/reader.js.map
Puppet27CookbookZhongwenban/js/reader.min.js
Puppet27CookbookZhongwenban/js/reader.min.map
Puppet27CookbookZhongwenban/js/hooks/__init__.py
Puppet27CookbookZhongwenban/js/hooks/extensions/__init__.py
Puppet27CookbookZhongwenban/js/hooks/extensions/highlight.js
Puppet27CookbookZhongwenban/js/libs/__init__.py
puppet_2_7_cookbook_zhongwenban-2024.3.2.0.dist-info/METADATA
puppet_2_7_cookbook_zhongwenban-2024.3.2.0.dist-info/WHEEL
puppet_2_7_cookbook_zhongwenban-2024.3.2.0.dist-info/entry_points.txt
puppet_2_7_cookbook_zhongwenban-2024.3.2.0.dist-info/top_level.txt
puppet_2_7_cookbook_zhongwenban-2024.3.2.0.dist-info/RECORD
